hts_forecast.py
hts_forecast-0.0.1.dist-info/LICENSE
hts_forecast-0.0.1.dist-info/METADATA
hts_forecast-0.0.1.dist-info/WHEEL
hts_forecast-0.0.1.dist-info/top_level.txt
hts_forecast-0.0.1.dist-info/RECORD
