Metadata-Version: 2.1
Name: hts-forecast
Version: 0.0.1
Summary: AUTO HIERARCHIAL TIME SERIES FORECASTING
Home-page: https://github.com/ramachaitanya0/auto_hts_package
Author: Ishita Roy,  Rama Chaitanya Karanam
Author-email: ramachaitanya0@gmail.com
License: MIT
Classifier: Programming Language :: Python :: 3 
Classifier: License :: OSI Approved :: MIT License
Classifier: Operating System :: OS Independent
License-File: LICENSE
Requires-Dist: pystan (==2.19.1.1)
Requires-Dist: scikit-learn (==1.0.2)
Requires-Dist: scikit-hts (==0.5.12)
Requires-Dist: arch (==5.2.0)
Requires-Dist: pmdarima (==1.8.5)
Requires-Dist: fbprophet (==0.7.1)
